{
  "resourceType" : "Parameters",
  "id" : "AlignmentResponseAlignedExample",
  "meta" : {
    "profile" : ["https://dsacms.github.io/cmmi-access-model/StructureDefinition/access-align-out"]
  },
  "parameter" : [{
    "name" : "result",
    "valueCodeableConcept" : {
      "coding" : [{
        "system" : "https://dsacms.github.io/cmmi-access-model/CodeSystem/ACCESSAlignmentResultCS",
        "code" : "aligned",
        "display" : "Aligned"
      }],
      "text" : "Patient is eligible and has been aligned so the ACCESS participant can now begin providing services to the patient under the model."
    }
  }]
}